mlflow_kernel/__init__.py
mlflow_kernel/__main__.py
mlflow_kernel/install.py
mlflow_kernel/kernel.json
mlflow_kernel/mlflow_kernel.py
mlflow_kernel-0.1.10.dist-info/LICENSE
mlflow_kernel-0.1.10.dist-info/METADATA
mlflow_kernel-0.1.10.dist-info/WHEEL
mlflow_kernel-0.1.10.dist-info/top_level.txt
mlflow_kernel-0.1.10.dist-info/RECORD
