Metadata-Version: 2.1
Name: mlflow-kernel
Version: 0.1.10
Summary: MLFlow kernel for jupyter
Home-page: UNKNOWN
Author: UNKNOWN
Author-email: UNKNOWN
License: UNKNOWN
Platform: UNKNOWN
Requires-Dist: infinstor-mlflow-plugin
Requires-Dist: ipykernel (>=6.0.0)
Requires-Dist: jupyter-client (<=6.99.99)
Requires-Dist: ipython-genutils
Requires-Dist: boto3
